ask_human_mcp/__init__.py
ask_human_mcp/server.py
ask_human_mcp-0.1.1.dist-info/licenses/LICENSE
ask_human_mcp-0.1.1.dist-info/METADATA
ask_human_mcp-0.1.1.dist-info/WHEEL
ask_human_mcp-0.1.1.dist-info/entry_points.txt
ask_human_mcp-0.1.1.dist-info/top_level.txt
ask_human_mcp-0.1.1.dist-info/RECORD
