Metadata-Version: 2.4
Name: ask-human-mcp
Version: 0.1.1
Summary: MCP server that lets AI agents escalate questions to humans
Author-email: Mason Yarbrough <mason@kallro.com>
License-Expression: MIT
Project-URL: Homepage, https://github.com/masony817/ask-human-mcp
Project-URL: Repository, https://github.com/masony817/ask-human-mcp.git
Project-URL: Documentation, https://github.com/masony817/ask-human-mcp#readme
Project-URL: Issues, https://github.com/masony817/ask-human-mcp/issues
Keywords: mcp,ai,human-in-the-loop,cursor,claude
Classifier: Development Status :: 4 - Beta
Classifier: Intended Audience :: Developers
Classifier: Programming Language :: Python :: 3
Classifier: Programming Language :: Python :: 3.8
Classifier: Programming Language :: Python :: 3.9
Classifier: Programming Language :: Python :: 3.10
Classifier: Programming Language :: Python :: 3.11
Classifier: Programming Language :: Python :: 3.12
Classifier: Topic :: Software Development
Classifier: Topic :: Scientific/Engineering :: Artificial Intelligence
Requires-Python: >=3.8
License-File: LICENSE
Requires-Dist: mcp>=1.0.0
Requires-Dist: watchdog>=3.0.0
Requires-Dist: fastapi>=0.100.0
Requires-Dist: uvicorn>=0.20.0
Requires-Dist: nest-asyncio>=1.5.0
Provides-Extra: dev
Requires-Dist: pytest>=7.0.0; extra == "dev"
Requires-Dist: pytest-asyncio>=0.21.0; extra == "dev"
Requires-Dist: black>=23.0.0; extra == "dev"
Requires-Dist: ruff>=0.1.0; extra == "dev"
Requires-Dist: mypy>=1.0.0; extra == "dev"
Dynamic: license-file
